LICENSE
MANIFEST.in
README.md
setup.cfg
setup.py
ucraft_unsplash_api.egg-info/PKG-INFO
ucraft_unsplash_api.egg-info/SOURCES.txt
ucraft_unsplash_api.egg-info/dependency_links.txt
ucraft_unsplash_api.egg-info/requires.txt
ucraft_unsplash_api.egg-info/top_level.txt
ucraft_unsplash_api.egg-info/zip-safe
unsplash/__init__.py
unsplash/api.py
unsplash/auth.py
unsplash/client.py
unsplash/collection.py
unsplash/errors.py
unsplash/models.py
unsplash/photo.py
unsplash/search.py
unsplash/stat.py
unsplash/user.py